{
  "actions": [],
  "allow_rename": 0,
  "custom": 0,
  "doctype": "DocType",
  "editable_grid": 0,
  "engine": "InnoDB",
  "fields": [
    {
      "fieldname": "type",
      "fieldtype": "Select",
      "in_list_view": 1,
      "label": "Type",
      "options": "Date\nDate Range\nWeekday",
      "reqd": 1
    },
    {
      "fieldname": "value",
      "fieldtype": "Data",
      "in_list_view": 1,
      "label": "Value",
      "read_only": 1,
      "virtual": 1,
      "depends_on": "eval: 1==0"
    },
    {
      "fieldname": "date_input",
      "fieldtype": "Date",
      "in_list_view": 0,
      "label": "Date",
      "virtual": 1,
      "depends_on": "eval: $.inArray(doc.type, ['Date Range', 'Date']) !== -1",
      "mandatory_depends_on": "eval: $.inArray(doc.type, ['Date Range', 'Date']) !== -1"
    },
    {
      "fieldname": "start_date",
      "fieldtype": "Date",
      "in_list_view": 0,
      "label": "From Date",
      "hidden": 1
    },
    {
      "fieldname": "end_date",
      "fieldtype": "Date",
      "in_list_view": 0,
      "label": "To Date",
      "hidden": 1
    },
    {
      "fieldname": "weekday",
      "fieldtype": "Select",
      "in_list_view": 0,
      "label": "Weekday",
      "options": "\nMonday\nTuesday\nWednesday\nThursday\nFriday\nSaturday\nSunday",
      "depends_on": "eval:doc.type == 'Weekday'",
      "mandatory_depends_on": "eval:doc.type == 'Weekday'"
    },
    {
      "fieldname": "rule",
      "fieldtype": "Select",
      "in_list_view": 1,
      "label": "Rule",
      "options": "Include\nExclude",
      "reqd": 1
    }
  ],
  "istable": 1,
  "module": "Easytix Booking",
  "name": "Date Rule",
  "permissions": [],
  "track_changes": 1,
  "track_views": 1
}
